{
  "IsRegenerate": false,
  "MenuPosition": "admin",
  "RelativeNamespace": "Account",
  "EntityName": "SaveItem",
  "EntityNamePlural": "SaveItems",
  "TableName": "SaveItems",
  "PrimaryKeyType": "long",
  "BaseClass": "AuditedEntity",
  "EntityHistory": false,
  "AutoMigration": false,
  "UpdateDatabase": false,
  "CreateUserInterface": true,
  "CreateViewOnly": true,
  "CreateExcelExport": true,
  "PagePermission": {
    "Host": true,
    "Tenant": true
  },
  "Properties": [],
  "NavigationProperties": [
    {
      "Namespace": "TepayLink.Sdisco.Products",
      "ForeignEntityName": "Product",
      "IdType": "long",
      "IsNullable": true,
      "PropertyName": "ProductId",
      "DisplayPropertyName": "Name",
      "DuplicationNumber": 0,
      "RelationType": "single"
    }
  ],
  "EnumDefinitions": []
}