{
  "IsRegenerate": true,
  "MenuPosition": "",
  "RelativeNamespace": "Account",
  "EntityName": "Wallet",
  "EntityNamePlural": "Wallets",
  "TableName": "Wallets",
  "PrimaryKeyType": "long",
  "BaseClass": "AuditedEntity",
  "EntityHistory": false,
  "AutoMigration": true,
  "UpdateDatabase": true,
  "CreateUserInterface": false,
  "CreateViewOnly": true,
  "CreateExcelExport": true,
  "PagePermission": {
    "Host": true,
    "Tenant": true
  },
  "Properties": [
    {
      "Name": "Balance",
      "Type": "decimal",
      "MaxLength": -1,
      "MinLength": -1,
      "Range": {
        "IsRangeSet": false,
        "MinimumValue": 0,
        "MaximumValue": 0
      },
      "Required": false,
      "Nullable": false,
      "Regex": "",
      "UserInterface": {
        "AdvancedFilter": true,
        "List": true,
        "CreateOrUpdate": true
      }
    },
    {
      "Name": "Type",
      "Type": "WalletTypeEnum",
      "MaxLength": -1,
      "MinLength": -1,
      "Range": {
        "IsRangeSet": false,
        "MinimumValue": 0,
        "MaximumValue": 0
      },
      "Required": false,
      "Nullable": false,
      "Regex": "",
      "UserInterface": {
        "AdvancedFilter": true,
        "List": true,
        "CreateOrUpdate": true
      }
    }
  ],
  "NavigationProperties": [
    {
      "Namespace": "TepayLink.Sdisco.Authorization.Users",
      "ForeignEntityName": "User",
      "IdType": "long",
      "IsNullable": true,
      "PropertyName": "UserId",
      "DisplayPropertyName": "Name",
      "DuplicationNumber": 0,
      "RelationType": "single"
    }
  ],
  "EnumDefinitions": [
    {
      "Name": "WalletTypeEnum",
      "Namespace": "TepayLink.Sdisco.Account",
      "EnumProperties": []
    }
  ]
}